{ "type": "FeatureCollection",
    "features": [
        {
            "type": "Feature",
            "geometry": {
                "type": "Point",
                "coordinates": [52.516667, 13.383333]
            },
            "properties": {
                "City": "Berlin",
                "April 2013": "Business Trip"
            }
        },
        {
            "type": "Feature",
            "geometry": {
                "type": "Point",
                "coordinates": [47.994722, 7.849722]
            },
            "properties": {
                "City": "Freiburg",
                "27 April 2013": "Business Trip. Celebration of the first birthday of MeinFernbus.de"
            }
        }
    ]
}
